{
  "sources": {
    "AdamStaya": {
      "checks": 6096,
      "consecutive_empty": 0,
      "consecutive_errors": 0,
      "last_checked_at": "2026-07-23T18:22:54.362748+00:00",
      "last_messages_count": 20,
      "last_problem_at": "2026-07-13T20:00:35.305104+00:00",
      "last_success_at": "2026-07-23T18:22:54.362748+00:00",
      "status": "ok",
      "successful_checks": 6095,
      "transport_outages": 2
    },
    "Artem1dacast": {
      "checks": 4008,
      "consecutive_empty": 0,
      "consecutive_errors": 0,
      "last_checked_at": "2026-07-23T18:22:54.364140+00:00",
      "last_messages_count": 11,
      "last_problem_at": "2026-07-20T00:00:08.160376+00:00",
      "last_success_at": "2026-07-23T18:22:54.364140+00:00",
      "status": "ok",
      "successful_checks": 4007
    },
    "Avtoritet06101": {
      "checks": 4008,
      "consecutive_empty": 0,
      "consecutive_errors": 0,
      "last_checked_at": "2026-07-23T18:22:54.364209+00:00",
      "last_messages_count": 20,
      "last_problem_at": "2026-07-22T05:44:59.944884+00:00",
      "last_success_at": "2026-07-23T18:22:54.364209+00:00",
      "status": "ok",
      "successful_checks": 4007
    },
    "BCLesports": {
      "checks": 4008,
      "consecutive_empty": 0,
      "consecutive_errors": 0,
      "last_checked_at": "2026-07-23T18:22:54.364222+00:00",
      "last_messages_count": 17,
      "last_success_at": "2026-07-23T18:22:54.364222+00:00",
      "status": "ok",
      "successful_checks": 4008
    },
    "BELKAKIBER": {
      "checks": 4008,
      "consecutive_empty": 0,
      "consecutive_errors": 0,
      "last_checked_at": "2026-07-23T18:22:54.364236+00:00",
      "last_messages_count": 11,
      "last_success_at": "2026-07-23T18:22:54.364236+00:00",
      "status": "ok",
      "successful_checks": 4008
    },
    "BetBoomPR": {
      "checks": 3946,
      "consecutive_empty": 0,
      "consecutive_errors": 0,
      "last_checked_at": "2026-07-23T18:22:54.364871+00:00",
      "last_messages_count": 19,
      "last_success_at": "2026-07-23T18:22:54.364871+00:00",
      "status": "ok",
      "successful_checks": 3946
    },
    "Blessmur_mlbb": {
      "checks": 4008,
      "consecutive_empty": 0,
      "consecutive_errors": 0,
      "last_checked_at": "2026-07-23T18:22:54.364249+00:00",
      "last_messages_count": 4,
      "last_success_at": "2026-07-23T18:22:54.364249+00:00",
      "status": "ok",
      "successful_checks": 4008
    },
    "Blindzonexbet": {
      "checks": 6096,
      "consecutive_empty": 0,
      "consecutive_errors": 0,
      "last_checked_at": "2026-07-23T18:22:54.362950+00:00",
      "last_messages_count": 19,
      "last_success_at": "2026-07-23T18:22:54.362950+00:00",
      "status": "ok",
      "successful_checks": 6096,
      "transport_outages": 2
    },
    "Breakevens": {
      "checks": 5897,
      "consecutive_empty": 0,
      "consecutive_errors": 0,
      "last_checked_at": "2026-07-23T18:22:54.363485+00:00",
      "last_messages_count": 18,
      "last_success_at": "2026-07-23T18:22:54.363485+00:00",
      "status": "ok",
      "successful_checks": 5897,
      "transport_outages": 2
    },
    "Cyberhero_mobilelegends": {
      "checks": 4008,
      "consecutive_empty": 0,
      "consecutive_errors": 0,
      "last_checked_at": "2026-07-23T18:22:54.364316+00:00",
      "last_messages_count": 20,
      "last_success_at": "2026-07-23T18:22:54.364316+00:00",
      "status": "ok",
      "successful_checks": 4008
    },
    "DayneezBet": {
      "checks": 6096,
      "consecutive_empty": 0,
      "consecutive_errors": 0,
      "last_checked_at": "2026-07-23T18:22:54.362965+00:00",
      "last_messages_count": 19,
      "last_success_at": "2026-07-23T18:22:54.362965+00:00",
      "status": "ok",
      "successful_checks": 6096,
      "transport_outages": 2
    },
    "EWC_betboom": {
      "checks": 5897,
      "consecutive_empty": 0,
      "consecutive_errors": 0,
      "last_checked_at": "2026-07-23T18:22:54.363528+00:00",
      "last_messages_count": 12,
      "last_success_at": "2026-07-23T18:22:54.363528+00:00",
      "status": "ok",
      "successful_checks": 5897,
      "transport_outages": 2
    },
    "EviLGrannY_WoT": {
      "checks": 4009,
      "consecutive_empty": 0,
      "consecutive_errors": 0,
      "last_checked_at": "2026-07-23T18:22:54.363872+00:00",
      "last_messages_count": 19,
      "last_success_at": "2026-07-23T18:22:54.363872+00:00",
      "status": "ok",
      "successful_checks": 4009
    },
    "False9Jersey": {
      "checks": 5897,
      "consecutive_empty": 0,
      "consecutive_errors": 0,
      "last_checked_at": "2026-07-23T18:22:54.363499+00:00",
      "last_messages_count": 4,
      "last_success_at": "2026-07-23T18:22:54.363499+00:00",
      "status": "ok",
      "successful_checks": 5897,
      "transport_outages": 2
    },
    "GromoZekaCS": {
      "checks": 4009,
      "consecutive_empty": 0,
      "consecutive_errors": 0,
      "last_checked_at": "2026-07-23T18:22:54.363981+00:00",
      "last_messages_count": 15,
      "last_success_at": "2026-07-23T18:22:54.363981+00:00",
      "status": "ok",
      "successful_checks": 4009
    },
    "IGMMLBB": {
      "checks": 4009,
      "consecutive_empty": 0,
      "consecutive_errors": 0,
      "last_checked_at": "2026-07-23T18:22:54.364008+00:00",
      "last_messages_count": 20,
      "last_problem_at": "2026-07-22T04:21:47.482082+00:00",
      "last_success_at": "2026-07-23T18:22:54.364008+00:00",
      "status": "ok",
      "successful_checks": 4008
    },
    "KRATtv": {
      "checks": 6096,
      "consecutive_empty": 0,
      "consecutive_errors": 0,
      "last_checked_at": "2026-07-23T18:22:54.363010+00:00",
      "last_messages_count": 20,
      "last_success_at": "2026-07-23T18:22:54.363010+00:00",
      "status": "ok",
      "successful_checks": 6096,
      "transport_outages": 2
    },
    "KeysieCloud": {
      "checks": 4008,
      "consecutive_empty": 0,
      "consecutive_errors": 0,
      "last_checked_at": "2026-07-23T18:22:54.364449+00:00",
      "last_messages_count": 11,
      "last_success_at": "2026-07-23T18:22:54.364449+00:00",
      "status": "ok",
      "successful_checks": 4008
    },
    "LPK_esport": {
      "checks": 4008,
      "consecutive_empty": 0,
      "consecutive_errors": 0,
      "last_checked_at": "2026-07-23T18:22:54.364517+00:00",
      "last_messages_count": 20,
      "last_success_at": "2026-07-23T18:22:54.364517+00:00",
      "status": "ok",
      "successful_checks": 4008
    },
    "LifeForSurf": {
      "checks": 4008,
      "consecutive_empty": 0,
      "consecutive_errors": 0,
      "last_checked_at": "2026-07-23T18:22:54.364490+00:00",
      "last_messages_count": 19,
      "last_success_at": "2026-07-23T18:22:54.364490+00:00",
      "status": "ok",
      "successful_checks": 4008
    },
    "LilCandyML": {
      "checks": 4008,
      "consecutive_empty": 0,
      "consecutive_errors": 0,
      "last_checked_at": "2026-07-23T18:22:54.364504+00:00",
      "last_messages_count": 19,
      "last_success_at": "2026-07-23T18:22:54.364504+00:00",
      "status": "ok",
      "successful_checks": 4008
    },
    "MARIOMAXTV": {
      "checks": 5770,
      "consecutive_empty": 0,
      "consecutive_errors": 0,
      "last_checked_at": "2026-07-23T18:22:54.363625+00:00",
      "last_messages_count": 17,
      "last_success_at": "2026-07-23T18:22:54.363625+00:00",
      "status": "ok",
      "successful_checks": 5770
    },
    "MPKBK2": {
      "checks": 4008,
      "consecutive_empty": 0,
      "consecutive_errors": 0,
      "last_checked_at": "2026-07-23T18:22:54.364612+00:00",
      "last_messages_count": 16,
      "last_success_at": "2026-07-23T18:22:54.364612+00:00",
      "status": "ok",
      "successful_checks": 4008
    },
    "NeretCast": {
      "checks": 6096,
      "consecutive_empty": 0,
      "consecutive_errors": 0,
      "last_checked_at": "2026-07-23T18:22:54.362763+00:00",
      "last_messages_count": 11,
      "last_problem_at": "2026-07-22T02:46:48.712912+00:00",
      "last_success_at": "2026-07-23T18:22:54.362763+00:00",
      "status": "ok",
      "successful_checks": 6094,
      "transport_outages": 2
    },
    "PAPAdota2": {
      "checks": 6096,
      "consecutive_empty": 0,
      "consecutive_errors": 0,
      "last_checked_at": "2026-07-23T18:22:54.362646+00:00",
      "last_messages_count": 18,
      "last_problem_at": "2026-07-19T04:15:10.911855+00:00",
      "last_success_at": "2026-07-23T18:22:54.362646+00:00",
      "status": "ok",
      "successful_checks": 6094,
      "transport_outages": 2
    },
    "PIVOVAR_Cast": {
      "checks": 2195,
      "consecutive_empty": 0,
      "consecutive_errors": 0,
      "last_checked_at": "2026-07-21T07:53:27.382988+00:00",
      "last_messages_count": 16,
      "last_success_at": "2026-07-21T07:53:27.382988+00:00",
      "status": "ok",
      "successful_checks": 2195
    },
    "RelaxCisBet": {
      "checks": 6096,
      "consecutive_empty": 0,
      "consecutive_errors": 0,
      "last_checked_at": "2026-07-23T18:22:54.363070+00:00",
      "last_messages_count": 19,
      "last_success_at": "2026-07-23T18:22:54.363070+00:00",
      "status": "ok",
      "successful_checks": 6096,
      "transport_outages": 2
    },
    "SashkaDestroyer": {
      "checks": 4008,
      "consecutive_empty": 0,
      "consecutive_errors": 0,
      "last_checked_at": "2026-07-23T18:22:54.364694+00:00",
      "last_messages_count": 20,
      "last_success_at": "2026-07-23T18:22:54.364694+00:00",
      "status": "ok",
      "successful_checks": 4008
    },
    "StrayDungeon228": {
      "checks": 6096,
      "consecutive_empty": 0,
      "consecutive_errors": 0,
      "last_checked_at": "2026-07-23T18:22:54.362778+00:00",
      "last_messages_count": 20,
      "last_problem_at": "2026-07-19T04:15:10.912036+00:00",
      "last_success_at": "2026-07-23T18:22:54.362778+00:00",
      "status": "ok",
      "successful_checks": 6094,
      "transport_outages": 2
    },
    "Team_Spirit_Official": {
      "checks": 3434,
      "consecutive_empty": 0,
      "consecutive_errors": 0,
      "last_checked_at": "2026-07-23T18:22:54.364898+00:00",
      "last_messages_count": 10,
      "last_problem_at": "2026-07-23T00:56:41.682143+00:00",
      "last_success_at": "2026-07-23T18:22:54.364898+00:00",
      "status": "ok",
      "successful_checks": 3432
    },
    "VooDooSh_Stream": {
      "checks": 4008,
      "consecutive_empty": 0,
      "consecutive_errors": 0,
      "last_checked_at": "2026-07-23T18:22:54.364803+00:00",
      "last_messages_count": 20,
      "last_problem_at": "2026-07-20T00:00:08.161222+00:00",
      "last_success_at": "2026-07-23T18:22:54.364803+00:00",
      "status": "ok",
      "successful_checks": 4007
    },
    "XDZachQ": {
      "checks": 4009,
      "consecutive_empty": 0,
      "consecutive_errors": 0,
      "last_checked_at": "2026-07-23T18:22:54.364125+00:00",
      "last_messages_count": 19,
      "last_success_at": "2026-07-23T18:22:54.364125+00:00",
      "status": "ok",
      "successful_checks": 4009
    },
    "Xoma_cs": {
      "checks": 4008,
      "consecutive_empty": 0,
      "consecutive_errors": 0,
      "last_checked_at": "2026-07-23T18:22:54.364844+00:00",
      "last_messages_count": 9,
      "last_success_at": "2026-07-23T18:22:54.364844+00:00",
      "status": "ok",
      "successful_checks": 4008
    },
    "YBNFedor": {
      "checks": 5873,
      "consecutive_empty": 0,
      "consecutive_errors": 0,
      "last_checked_at": "2026-07-23T18:22:54.363331+00:00",
      "last_messages_count": 20,
      "last_success_at": "2026-07-23T18:22:54.363331+00:00",
      "status": "ok",
      "successful_checks": 5873
    },
    "ZZoneRM": {
      "checks": 6096,
      "consecutive_empty": 0,
      "consecutive_errors": 0,
      "last_checked_at": "2026-07-23T18:22:54.363156+00:00",
      "last_messages_count": 14,
      "last_success_at": "2026-07-23T18:22:54.363156+00:00",
      "status": "ok",
      "successful_checks": 6096,
      "transport_outages": 2
    },
    "acoolbazarit": {
      "checks": 6096,
      "consecutive_empty": 0,
      "consecutive_errors": 0,
      "last_checked_at": "2026-07-23T18:22:54.362872+00:00",
      "last_messages_count": 20,
      "last_success_at": "2026-07-23T18:22:54.362872+00:00",
      "status": "ok",
      "successful_checks": 6096,
      "transport_outages": 2
    },
    "adekvatik": {
      "checks": 5770,
      "consecutive_empty": 0,
      "consecutive_errors": 0,
      "last_checked_at": "2026-07-23T18:22:54.363640+00:00",
      "last_messages_count": 20,
      "last_success_at": "2026-07-23T18:22:54.363640+00:00",
      "status": "ok",
      "successful_checks": 5770
    },
    "alex_white_official": {
      "checks": 3434,
      "consecutive_empty": 0,
      "consecutive_errors": 0,
      "last_checked_at": "2026-07-23T18:22:54.364911+00:00",
      "last_messages_count": 20,
      "last_problem_at": "2026-07-22T07:42:26.994225+00:00",
      "last_success_at": "2026-07-23T18:22:54.364911+00:00",
      "status": "ok",
      "successful_checks": 3433
    },
    "amam0610": {
      "checks": 6096,
      "consecutive_empty": 0,
      "consecutive_errors": 0,
      "last_checked_at": "2026-07-23T18:22:54.363286+00:00",
      "last_messages_count": 20,
      "last_success_at": "2026-07-23T18:22:54.363286+00:00",
      "status": "ok",
      "successful_checks": 6096,
      "transport_outages": 2
    },
    "arszeeqq": {
      "checks": 4009,
      "consecutive_empty": 0,
      "consecutive_errors": 0,
      "last_checked_at": "2026-07-23T18:22:54.363779+00:00",
      "last_messages_count": 20,
      "last_success_at": "2026-07-23T18:22:54.363779+00:00",
      "status": "ok",
      "successful_checks": 4009
    },
    "artemkef": {
      "checks": 5897,
      "consecutive_empty": 0,
      "consecutive_errors": 0,
      "last_checked_at": "2026-07-23T18:22:54.363456+00:00",
      "last_messages_count": 19,
      "last_success_at": "2026-07-23T18:22:54.363456+00:00",
      "status": "ok",
      "successful_checks": 5897,
      "transport_outages": 2
    },
    "aterionlegends": {
      "checks": 4008,
      "consecutive_empty": 0,
      "consecutive_errors": 0,
      "last_checked_at": "2026-07-23T18:22:54.364154+00:00",
      "last_messages_count": 20,
      "last_success_at": "2026-07-23T18:22:54.364154+00:00",
      "status": "ok",
      "successful_checks": 4008
    },
    "aunkereEZ": {
      "checks": 6096,
      "consecutive_empty": 0,
      "consecutive_errors": 0,
      "last_checked_at": "2026-07-23T18:22:54.362717+00:00",
      "last_messages_count": 20,
      "last_problem_at": "2026-07-19T04:15:10.911959+00:00",
      "last_success_at": "2026-07-23T18:22:54.362717+00:00",
      "status": "ok",
      "successful_checks": 6094,
      "transport_outages": 2
    },
    "aunkeretg": {
      "checks": 6096,
      "consecutive_empty": 0,
      "consecutive_errors": 0,
      "last_checked_at": "2026-07-23T18:22:54.363171+00:00",
      "last_messages_count": 20,
      "last_success_at": "2026-07-23T18:22:54.363171+00:00",
      "status": "ok",
      "successful_checks": 6096,
      "transport_outages": 2
    },
    "autodestruction": {
      "checks": 4008,
      "consecutive_empty": 0,
      "consecutive_errors": 0,
      "last_checked_at": "2026-07-23T18:22:54.364167+00:00",
      "last_messages_count": 11,
      "last_success_at": "2026-07-23T18:22:54.364167+00:00",
      "status": "ok",
      "successful_checks": 4008
    },
    "ave_rim": {
      "checks": 4008,
      "consecutive_empty": 0,
      "consecutive_errors": 0,
      "last_checked_at": "2026-07-23T18:22:54.364182+00:00",
      "last_messages_count": 11,
      "last_success_at": "2026-07-23T18:22:54.364182+00:00",
      "status": "ok",
      "successful_checks": 4008
    },
    "aviciixd": {
      "checks": 6096,
      "consecutive_empty": 0,
      "consecutive_errors": 0,
      "last_checked_at": "2026-07-23T18:22:54.362934+00:00",
      "last_messages_count": 20,
      "last_success_at": "2026-07-23T18:22:54.362934+00:00",
      "status": "ok",
      "successful_checks": 6096,
      "transport_outages": 2
    },
    "avstriez": {
      "checks": 4008,
      "consecutive_empty": 0,
      "consecutive_errors": 0,
      "last_checked_at": "2026-07-23T18:22:54.364195+00:00",
      "last_messages_count": 20,
      "last_problem_at": "2026-07-20T00:00:08.160461+00:00",
      "last_success_at": "2026-07-23T18:22:54.364195+00:00",
      "status": "ok",
      "successful_checks": 4007
    },
    "ayukifunpage": {
      "checks": 1263,
      "consecutive_empty": 0,
      "consecutive_errors": 0,
      "last_checked_at": "2026-07-23T18:22:54.364965+00:00",
      "last_messages_count": 20,
      "last_success_at": "2026-07-23T18:22:54.364965+00:00",
      "status": "ok",
      "successful_checks": 1263
    },
    "bbteamcs2": {
      "checks": 5897,
      "consecutive_empty": 0,
      "consecutive_errors": 0,
      "last_checked_at": "2026-07-23T18:22:54.363470+00:00",
      "last_messages_count": 2,
      "last_success_at": "2026-07-23T18:22:54.363470+00:00",
      "status": "ok",
      "successful_checks": 5897,
      "transport_outages": 2
    },
    "beardserklife": {
      "checks": 4009,
      "consecutive_empty": 0,
      "consecutive_errors": 0,
      "last_checked_at": "2026-07-23T18:22:54.363792+00:00",
      "last_messages_count": 11,
      "last_success_at": "2026-07-23T18:22:54.363792+00:00",
      "status": "ok",
      "successful_checks": 4009
    },
    "betbistTV": {
      "checks": 5380,
      "consecutive_empty": 0,
      "consecutive_errors": 0,
      "last_checked_at": "2026-07-23T18:22:54.363751+00:00",
      "last_messages_count": 18,
      "last_problem_at": "2026-07-22T04:18:43.745866+00:00",
      "last_success_at": "2026-07-23T18:22:54.363751+00:00",
      "status": "ok",
      "successful_checks": 5379
    },
    "betboom_baza": {
      "checks": 5721,
      "consecutive_empty": 0,
      "consecutive_errors": 0,
      "last_checked_at": "2026-07-23T18:22:54.363682+00:00",
      "last_messages_count": 20,
      "last_success_at": "2026-07-23T18:22:54.363682+00:00",
      "status": "ok",
      "successful_checks": 5721
    },
    "betboom_esports": {
      "checks": 5873,
      "consecutive_empty": 0,
      "consecutive_errors": 0,
      "last_checked_at": "2026-07-23T18:22:54.363387+00:00",
      "last_messages_count": 20,
      "last_problem_at": "2026-07-23T00:56:41.680138+00:00",
      "last_success_at": "2026-07-23T18:22:54.363387+00:00",
      "status": "ok",
      "successful_checks": 5872
    },
    "betboom_esports_cs": {
      "checks": 5873,
      "consecutive_empty": 0,
      "consecutive_errors": 0,
      "last_checked_at": "2026-07-23T18:22:54.363402+00:00",
      "last_messages_count": 20,
      "last_success_at": "2026-07-23T18:22:54.363402+00:00",
      "status": "ok",
      "successful_checks": 5873
    },
    "betboomru": {
      "checks": 5873,
      "consecutive_empty": 0,
      "consecutive_errors": 0,
      "last_checked_at": "2026-07-23T18:22:54.363359+00:00",
      "last_messages_count": 20,
      "last_success_at": "2026-07-23T18:22:54.363359+00:00",
      "status": "ok",
      "successful_checks": 5873
    },
    "betboomstreamersbattle": {
      "checks": 5873,
      "consecutive_empty": 0,
      "consecutive_errors": 0,
      "last_checked_at": "2026-07-23T18:22:54.363374+00:00",
      "last_messages_count": 20,
      "last_success_at": "2026-07-23T18:22:54.363374+00:00",
      "status": "ok",
      "successful_checks": 5873
    },
    "betboomteam": {
      "checks": 5873,
      "consecutive_empty": 0,
      "consecutive_errors": 0,
      "last_checked_at": "2026-07-23T18:22:54.363429+00:00",
      "last_messages_count": 16,
      "last_success_at": "2026-07-23T18:22:54.363429+00:00",
      "status": "ok",
      "successful_checks": 5873
    },
    "betboomteamcs2": {
      "checks": 5873,
      "consecutive_empty": 0,
      "consecutive_errors": 0,
      "last_checked_at": "2026-07-23T18:22:54.363443+00:00",
      "last_messages_count": 20,
      "last_problem_at": "2026-07-23T07:57:23.751710+00:00",
      "last_success_at": "2026-07-23T18:22:54.363443+00:00",
      "status": "ok",
      "successful_checks": 5872
    },
    "bettingmedialeague": {
      "checks": 4009,
      "consecutive_empty": 0,
      "consecutive_errors": 0,
      "last_checked_at": "2026-07-23T18:22:54.363805+00:00",
      "last_messages_count": 19,
      "last_success_at": "2026-07-23T18:22:54.363805+00:00",
      "status": "ok",
      "successful_checks": 4009
    },
    "blast_betboom": {
      "checks": 5873,
      "consecutive_empty": 0,
      "consecutive_errors": 0,
      "last_checked_at": "2026-07-23T18:22:54.363415+00:00",
      "last_messages_count": 20,
      "last_success_at": "2026-07-23T18:22:54.363415+00:00",
      "status": "ok",
      "successful_checks": 5873
    },
    "blindzonexgod": {
      "checks": 6096,
      "consecutive_empty": 0,
      "consecutive_errors": 0,
      "last_checked_at": "2026-07-23T18:22:54.363214+00:00",
      "last_messages_count": 18,
      "last_success_at": "2026-07-23T18:22:54.363214+00:00",
      "status": "ok",
      "successful_checks": 6096,
      "transport_outages": 2
    },
    "boltcast": {
      "checks": 6096,
      "consecutive_empty": 0,
      "consecutive_errors": 0,
      "last_checked_at": "2026-07-23T18:22:54.362699+00:00",
      "last_messages_count": 18,
      "last_problem_at": "2026-07-19T04:15:10.911936+00:00",
      "last_success_at": "2026-07-23T18:22:54.362699+00:00",
      "status": "ok",
      "successful_checks": 6094,
      "transport_outages": 2
    },
    "burdakekw": {
      "checks": 6096,
      "consecutive_empty": 0,
      "consecutive_errors": 0,
      "last_checked_at": "2026-07-23T18:22:54.363041+00:00",
      "last_messages_count": 20,
      "last_success_at": "2026-07-23T18:22:54.363041+00:00",
      "status": "ok",
      "successful_checks": 6096,
      "transport_outages": 2
    },
    "cakestreampage": {
      "checks": 4009,
      "consecutive_empty": 0,
      "consecutive_errors": 0,
      "last_checked_at": "2026-07-23T18:22:54.363819+00:00",
      "last_messages_count": 20,
      "last_success_at": "2026-07-23T18:22:54.363819+00:00",
      "status": "ok",
      "successful_checks": 4009
    },
    "cct_betboom": {
      "checks": 1197,
      "consecutive_empty": 0,
      "consecutive_errors": 0,
      "last_checked_at": "2026-07-23T18:22:54.364992+00:00",
      "last_messages_count": 20,
      "last_success_at": "2026-07-23T18:22:54.364992+00:00",
      "status": "ok",
      "successful_checks": 1197
    },
    "chiilstreeamML": {
      "checks": 4009,
      "consecutive_empty": 0,
      "consecutive_errors": 0,
      "last_checked_at": "2026-07-23T18:22:54.363832+00:00",
      "last_messages_count": 13,
      "last_success_at": "2026-07-23T18:22:54.363832+00:00",
      "status": "ok",
      "successful_checks": 4009
    },
    "chopperinho": {
      "checks": 5380,
      "consecutive_empty": 0,
      "consecutive_errors": 0,
      "last_checked_at": "2026-07-23T18:22:54.363696+00:00",
      "last_messages_count": 7,
      "last_success_at": "2026-07-23T18:22:54.363696+00:00",
      "status": "ok",
      "successful_checks": 5380
    },
    "chopperis": {
      "checks": 6096,
      "consecutive_empty": 0,
      "consecutive_errors": 0,
      "last_checked_at": "2026-07-23T18:22:54.362888+00:00",
      "last_messages_count": 20,
      "last_success_at": "2026-07-23T18:22:54.362888+00:00",
      "status": "ok",
      "successful_checks": 6096,
      "transport_outages": 2
    },
    "clife_cs2": {
      "checks": 4008,
      "consecutive_empty": 0,
      "consecutive_errors": 0,
      "last_checked_at": "2026-07-23T18:22:54.364262+00:00",
      "last_messages_count": 13,
      "last_problem_at": "2026-07-22T07:55:40.785023+00:00",
      "last_success_at": "2026-07-23T18:22:54.364262+00:00",
      "status": "ok",
      "successful_checks": 4007
    },
    "cscis": {
      "checks": 4008,
      "consecutive_empty": 0,
      "consecutive_errors": 0,
      "last_checked_at": "2026-07-23T18:22:54.364276+00:00",
      "last_messages_count": 11,
      "last_success_at": "2026-07-23T18:22:54.364276+00:00",
      "status": "ok",
      "successful_checks": 4008
    },
    "csgobet": {
      "checks": 4008,
      "consecutive_empty": 0,
      "consecutive_errors": 0,
      "last_checked_at": "2026-07-23T18:22:54.364289+00:00",
      "last_messages_count": 20,
      "last_success_at": "2026-07-23T18:22:54.364289+00:00",
      "status": "ok",
      "successful_checks": 4008
    },
    "ct0mislove": {
      "checks": 6096,
      "consecutive_empty": 0,
      "consecutive_errors": 0,
      "last_checked_at": "2026-07-23T18:22:54.363200+00:00",
      "last_messages_count": 20,
      "last_success_at": "2026-07-23T18:22:54.363200+00:00",
      "status": "ok",
      "successful_checks": 6096,
      "transport_outages": 2
    },
    "cybercracken": {
      "checks": 4008,
      "consecutive_empty": 0,
      "consecutive_errors": 0,
      "last_checked_at": "2026-07-23T18:22:54.364303+00:00",
      "last_messages_count": 18,
      "last_problem_at": "2026-07-20T00:00:08.160597+00:00",
      "last_success_at": "2026-07-23T18:22:54.364303+00:00",
      "status": "ok",
      "successful_checks": 4007
    },
    "cyberheromlbb": {
      "checks": 4008,
      "consecutive_empty": 0,
      "consecutive_errors": 0,
      "last_checked_at": "2026-07-23T18:22:54.364330+00:00",
      "last_messages_count": 20,
      "last_problem_at": "2026-07-22T22:09:15.414128+00:00",
      "last_success_at": "2026-07-23T18:22:54.364330+00:00",
      "status": "ok",
      "successful_checks": 4007
    },
    "dadtex": {
      "checks": 3577,
      "consecutive_empty": 0,
      "consecutive_errors": 0,
      "last_checked_at": "2026-07-23T18:22:54.364884+00:00",
      "last_messages_count": 17,
      "last_success_at": "2026-07-23T18:22:54.364884+00:00",
      "status": "ok",
      "successful_checks": 3577
    },
    "danila_gorilla": {
      "checks": 6096,
      "consecutive_empty": 0,
      "consecutive_errors": 0,
      "last_checked_at": "2026-07-23T18:22:54.362979+00:00",
      "last_messages_count": 20,
      "last_problem_at": "2026-07-22T04:33:54.062847+00:00",
      "last_success_at": "2026-07-23T18:22:54.362979+00:00",
      "status": "ok",
      "successful_checks": 6095,
      "transport_outages": 2
    },
    "danzelpodval": {
      "checks": 4009,
      "consecutive_empty": 0,
      "consecutive_errors": 0,
      "last_checked_at": "2026-07-23T18:22:54.363845+00:00",
      "last_messages_count": 20,
      "last_success_at": "2026-07-23T18:22:54.363845+00:00",
      "status": "ok",
      "successful_checks": 4009
    },
    "dartwager": {
      "checks": 6096,
      "consecutive_empty": 0,
      "consecutive_errors": 0,
      "last_checked_at": "2026-07-23T18:22:54.363272+00:00",
      "last_messages_count": 18,
      "last_success_at": "2026-07-23T18:22:54.363272+00:00",
      "status": "ok",
      "successful_checks": 6096,
      "transport_outages": 2
    },
    "dayneZz": {
      "checks": 6096,
      "consecutive_empty": 0,
      "consecutive_errors": 0,
      "last_checked_at": "2026-07-23T18:22:54.363228+00:00",
      "last_messages_count": 19,
      "last_problem_at": "2026-07-21T23:07:05.355807+00:00",
      "last_success_at": "2026-07-23T18:22:54.363228+00:00",
      "status": "ok",
      "successful_checks": 6095,
      "transport_outages": 2
    },
    "dekocs": {
      "checks": 6096,
      "consecutive_empty": 0,
      "consecutive_errors": 0,
      "last_checked_at": "2026-07-23T18:22:54.362826+00:00",
      "last_messages_count": 20,
      "last_success_at": "2026-07-23T18:22:54.362826+00:00",
      "status": "ok",
      "successful_checks": 6096,
      "transport_outages": 2
    },
    "dekocsoff": {
      "checks": 6096,
      "consecutive_empty": 0,
      "consecutive_errors": 0,
      "last_checked_at": "2026-07-23T18:22:54.363185+00:00",
      "last_messages_count": 20,
      "last_success_at": "2026-07-23T18:22:54.363185+00:00",
      "status": "ok",
      "successful_checks": 6096,
      "transport_outages": 2
    },
    "dmitrylebwa": {
      "checks": 4009,
      "consecutive_empty": 0,
      "consecutive_errors": 0,
      "last_checked_at": "2026-07-23T18:22:54.363859+00:00",
      "last_messages_count": 19,
      "last_success_at": "2026-07-23T18:22:54.363859+00:00",
      "status": "ok",
      "successful_checks": 4009
    },
    "dyrachyo": {
      "checks": 6096,
      "consecutive_empty": 0,
      "consecutive_errors": 0,
      "last_checked_at": "2026-07-23T18:22:54.362623+00:00",
      "last_messages_count": 7,
      "last_problem_at": "2026-07-13T20:00:35.304945+00:00",
      "last_success_at": "2026-07-23T18:22:54.362623+00:00",
      "status": "ok",
      "successful_checks": 6095,
      "transport_outages": 2
    },
    "dyrachyobets": {
      "checks": 5380,
      "consecutive_empty": 0,
      "consecutive_errors": 0,
      "last_checked_at": "2026-07-23T18:22:54.363737+00:00",
      "last_messages_count": 19,
      "last_success_at": "2026-07-23T18:22:54.363737+00:00",
      "status": "ok",
      "successful_checks": 5380
    },
    "etozhekoval": {
      "checks": 5109,
      "consecutive_empty": 0,
      "consecutive_errors": 0,
      "last_checked_at": "2026-07-23T18:22:54.363765+00:00",
      "last_messages_count": 20,
      "last_success_at": "2026-07-23T18:22:54.363765+00:00",
      "status": "ok",
      "successful_checks": 5109
    },
    "exilemusic13": {
      "checks": 4009,
      "consecutive_empty": 0,
      "consecutive_errors": 0,
      "last_checked_at": "2026-07-23T18:22:54.363886+00:00",
      "last_messages_count": 19,
      "last_problem_at": "2026-07-23T01:09:45.180863+00:00",
      "last_success_at": "2026-07-23T18:22:54.363886+00:00",
      "status": "ok",
      "successful_checks": 4007
    },
    "f_1ncsgo": {
      "checks": 4008,
      "consecutive_empty": 0,
      "consecutive_errors": 0,
      "last_checked_at": "2026-07-23T18:22:54.364343+00:00",
      "last_messages_count": 17,
      "last_success_at": "2026-07-23T18:22:54.364343+00:00",
      "status": "ok",
      "successful_checks": 4008
    },
    "fishmandota2": {
      "checks": 4009,
      "consecutive_empty": 0,
      "consecutive_errors": 0,
      "last_checked_at": "2026-07-23T18:22:54.363900+00:00",
      "last_messages_count": 20,
      "last_success_at": "2026-07-23T18:22:54.363900+00:00",
      "status": "ok",
      "successful_checks": 4009
    },
    "flamebaker": {
      "checks": 4009,
      "consecutive_empty": 0,
      "consecutive_errors": 0,
      "last_checked_at": "2026-07-23T18:22:54.363914+00:00",
      "last_messages_count": 19,
      "last_problem_at": "2026-07-20T00:00:08.160077+00:00",
      "last_success_at": "2026-07-23T18:22:54.363914+00:00",
      "status": "ok",
      "successful_checks": 4008
    },
    "flashynthen1ght": {
      "checks": 4009,
      "consecutive_empty": 0,
      "consecutive_errors": 0,
      "last_checked_at": "2026-07-23T18:22:54.363927+00:00",
      "last_messages_count": 15,
      "last_success_at": "2026-07-23T18:22:54.363927+00:00",
      "status": "ok",
      "successful_checks": 4009
    },
    "flouzer666": {
      "checks": 4009,
      "consecutive_empty": 0,
      "consecutive_errors": 0,
      "last_checked_at": "2026-07-23T18:22:54.363941+00:00",
      "last_messages_count": 16,
      "last_problem_at": "2026-07-22T06:34:20.849059+00:00",
      "last_success_at": "2026-07-23T18:22:54.363941+00:00",
      "status": "ok",
      "successful_checks": 4007
    },
    "fmeleague": {
      "checks": 4008,
      "consecutive_empty": 0,
      "consecutive_errors": 0,
      "last_checked_at": "2026-07-23T18:22:54.364356+00:00",
      "last_messages_count": 20,
      "last_success_at": "2026-07-23T18:22:54.364356+00:00",
      "status": "ok",
      "successful_checks": 4008
    },
    "fonbetesports": {
      "checks": 4009,
      "consecutive_empty": 0,
      "consecutive_errors": 0,
      "last_checked_at": "2026-07-23T18:22:54.363954+00:00",
      "last_messages_count": 19,
      "last_success_at": "2026-07-23T18:22:54.363954+00:00",
      "status": "ok",
      "successful_checks": 4009
    },
    "fonpass": {
      "checks": 3946,
      "consecutive_empty": 0,
      "consecutive_errors": 0,
      "last_checked_at": "2026-07-23T18:22:54.364857+00:00",
      "last_messages_count": 19,
      "last_success_at": "2026-07-23T18:22:54.364857+00:00",
      "status": "ok",
      "successful_checks": 3946
    },
    "geassamlbb": {
      "checks": 4008,
      "consecutive_empty": 0,
      "consecutive_errors": 0,
      "last_checked_at": "2026-07-23T18:22:54.364370+00:00",
      "last_messages_count": 20,
      "last_success_at": "2026-07-23T18:22:54.364370+00:00",
      "status": "ok",
      "successful_checks": 4008
    },
    "gexsuntv": {
      "checks": 4008,
      "consecutive_empty": 0,
      "consecutive_errors": 0,
      "last_checked_at": "2026-07-23T18:22:54.364383+00:00",
      "last_messages_count": 20,
      "last_success_at": "2026-07-23T18:22:54.364383+00:00",
      "status": "ok",
      "successful_checks": 4008
    },
    "gluck_es": {
      "checks": 4008,
      "consecutive_empty": 0,
      "consecutive_errors": 0,
      "last_checked_at": "2026-07-23T18:22:54.364396+00:00",
      "last_messages_count": 20,
      "last_success_at": "2026-07-23T18:22:54.364396+00:00",
      "status": "ok",
      "successful_checks": 4008
    },
    "golospokera": {
      "checks": 4009,
      "consecutive_empty": 0,
      "consecutive_errors": 0,
      "last_checked_at": "2026-07-23T18:22:54.363967+00:00",
      "last_messages_count": 20,
      "last_success_at": "2026-07-23T18:22:54.363967+00:00",
      "status": "ok",
      "successful_checks": 4009
    },
    "gorilla_armor": {
      "checks": 6096,
      "consecutive_empty": 0,
      "consecutive_errors": 0,
      "last_checked_at": "2026-07-23T18:22:54.362995+00:00",
      "last_messages_count": 20,
      "last_success_at": "2026-07-23T18:22:54.362995+00:00",
      "status": "ok",
      "successful_checks": 6096,
      "transport_outages": 2
    },
    "graynetv": {
      "checks": 4008,
      "consecutive_empty": 0,
      "consecutive_errors": 0,
      "last_checked_at": "2026-07-23T18:22:54.364410+00:00",
      "last_messages_count": 14,
      "last_success_at": "2026-07-23T18:22:54.364410+00:00",
      "status": "ok",
      "successful_checks": 4008
    },
    "gshikaryan": {
      "checks": 6096,
      "consecutive_empty": 0,
      "consecutive_errors": 0,
      "last_checked_at": "2026-07-23T18:22:54.363141+00:00",
      "last_messages_count": 19,
      "last_problem_at": "2026-07-23T00:44:22.963095+00:00",
      "last_success_at": "2026-07-23T18:22:54.363141+00:00",
      "status": "ok",
      "successful_checks": 6095,
      "transport_outages": 2
    },
    "happyzerg11": {
      "checks": 4009,
      "consecutive_empty": 0,
      "consecutive_errors": 0,
      "last_checked_at": "2026-07-23T18:22:54.363994+00:00",
      "last_messages_count": 20,
      "last_success_at": "2026-07-23T18:22:54.363994+00:00",
      "status": "ok",
      "successful_checks": 4009
    },
    "helin139burmalda": {
      "checks": 75,
      "consecutive_empty": 0,
      "consecutive_errors": 0,
      "last_checked_at": "2026-07-23T18:22:54.365005+00:00",
      "last_messages_count": 20,
      "last_success_at": "2026-07-23T18:22:54.365005+00:00",
      "status": "ok",
      "successful_checks": 75
    },
    "homakolesa": {
      "checks": 6096,
      "consecutive_empty": 0,
      "consecutive_errors": 0,
      "last_checked_at": "2026-07-23T18:22:54.363242+00:00",
      "last_messages_count": 20,
      "last_success_at": "2026-07-23T18:22:54.363242+00:00",
      "status": "ok",
      "successful_checks": 6096,
      "transport_outages": 2
    },
    "hoochcs2": {
      "checks": 6096,
      "consecutive_empty": 0,
      "consecutive_errors": 0,
      "last_checked_at": "2026-07-23T18:22:54.362903+00:00",
      "last_messages_count": 19,
      "last_success_at": "2026-07-23T18:22:54.362903+00:00",
      "status": "ok",
      "successful_checks": 6096,
      "transport_outages": 2
    },
    "igmtv": {
      "checks": 4008,
      "consecutive_empty": 0,
      "consecutive_errors": 0,
      "last_checked_at": "2026-07-23T18:22:54.364423+00:00",
      "last_messages_count": 14,
      "last_success_at": "2026-07-23T18:22:54.364423+00:00",
      "status": "ok",
      "successful_checks": 4008
    },
    "ihuntnoobs": {
      "checks": 6096,
      "consecutive_empty": 0,
      "consecutive_errors": 0,
      "last_checked_at": "2026-07-23T18:22:54.362810+00:00",
      "last_messages_count": 20,
      "last_success_at": "2026-07-23T18:22:54.362810+00:00",
      "status": "ok",
      "successful_checks": 6096,
      "transport_outages": 2
    },
    "jestercast": {
      "checks": 5767,
      "consecutive_empty": 0,
      "consecutive_errors": 0,
      "last_checked_at": "2026-07-23T18:22:54.363654+00:00",
      "last_messages_count": 20,
      "last_problem_at": "2026-07-23T00:11:55.346357+00:00",
      "last_success_at": "2026-07-23T18:22:54.363654+00:00",
      "status": "ok",
      "successful_checks": 5766
    },
    "jetnizestream": {
      "checks": 4009,
      "consecutive_empty": 0,
      "consecutive_errors": 0,
      "last_checked_at": "2026-07-23T18:22:54.364021+00:00",
      "last_messages_count": 20,
      "last_problem_at": "2026-07-20T00:00:08.160236+00:00",
      "last_success_at": "2026-07-23T18:22:54.364021+00:00",
      "status": "ok",
      "successful_checks": 4008
    },
    "kdh440cast": {
      "checks": 4009,
      "consecutive_empty": 0,
      "consecutive_errors": 0,
      "last_checked_at": "2026-07-23T18:22:54.364035+00:00",
      "last_messages_count": 20,
      "last_problem_at": "2026-07-23T07:53:20.785681+00:00",
      "last_success_at": "2026-07-23T18:22:54.364035+00:00",
      "status": "ok",
      "successful_checks": 4008
    },
    "keendabol": {
      "checks": 4008,
      "consecutive_empty": 0,
      "consecutive_errors": 0,
      "last_checked_at": "2026-07-23T18:22:54.364436+00:00",
      "last_messages_count": 20,
      "last_success_at": "2026-07-23T18:22:54.364436+00:00",
      "status": "ok",
      "successful_checks": 4008
    },
    "kiraenn": {
      "checks": 4009,
      "consecutive_empty": 0,
      "consecutive_errors": 0,
      "last_checked_at": "2026-07-23T18:22:54.364048+00:00",
      "last_messages_count": 13,
      "last_success_at": "2026-07-23T18:22:54.364048+00:00",
      "status": "ok",
      "successful_checks": 4009
    },
    "kiritych1": {
      "checks": 5897,
      "consecutive_empty": 0,
      "consecutive_errors": 0,
      "last_checked_at": "2026-07-23T18:22:54.363541+00:00",
      "last_messages_count": 20,
      "last_problem_at": "2026-07-21T22:44:46.197631+00:00",
      "last_success_at": "2026-07-23T18:22:54.363541+00:00",
      "status": "ok",
      "successful_checks": 5896,
      "transport_outages": 2
    },
    "kolesaBB": {
      "checks": 6096,
      "consecutive_empty": 0,
      "consecutive_errors": 0,
      "last_checked_at": "2026-07-23T18:22:54.363301+00:00",
      "last_messages_count": 15,
      "last_success_at": "2026-07-23T18:22:54.363301+00:00",
      "status": "ok",
      "successful_checks": 6096,
      "transport_outages": 2
    },
    "kr4syy": {
      "checks": 4008,
      "consecutive_empty": 0,
      "consecutive_errors": 0,
      "last_checked_at": "2026-07-23T18:22:54.364463+00:00",
      "last_messages_count": 15,
      "last_success_at": "2026-07-23T18:22:54.364463+00:00",
      "status": "ok",
      "successful_checks": 4008
    },
    "kzmantis": {
      "checks": 6096,
      "consecutive_empty": 0,
      "consecutive_errors": 0,
      "last_checked_at": "2026-07-23T18:22:54.363085+00:00",
      "last_messages_count": 20,
      "last_success_at": "2026-07-23T18:22:54.363085+00:00",
      "status": "ok",
      "successful_checks": 6096,
      "transport_outages": 2
    },
    "ladlda": {
      "checks": 5897,
      "consecutive_empty": 0,
      "consecutive_errors": 0,
      "last_checked_at": "2026-07-23T18:22:54.363556+00:00",
      "last_messages_count": 5,
      "last_success_at": "2026-07-23T18:22:54.363556+00:00",
      "status": "ok",
      "successful_checks": 5897,
      "transport_outages": 2
    },
    "lasthero_dota": {
      "checks": 4008,
      "consecutive_empty": 0,
      "consecutive_errors": 0,
      "last_checked_at": "2026-07-23T18:22:54.364476+00:00",
      "last_messages_count": 17,
      "last_success_at": "2026-07-23T18:22:54.364476+00:00",
      "status": "ok",
      "successful_checks": 4008
    },
    "lukawahouse": {
      "checks": 5897,
      "consecutive_empty": 0,
      "consecutive_errors": 0,
      "last_checked_at": "2026-07-23T18:22:54.363570+00:00",
      "last_messages_count": 10,
      "last_success_at": "2026-07-23T18:22:54.363570+00:00",
      "status": "ok",
      "successful_checks": 5897,
      "transport_outages": 2
    },
    "m3traNeoStream": {
      "checks": 5868,
      "consecutive_empty": 0,
      "consecutive_errors": 0,
      "last_checked_at": "2026-07-23T18:22:54.363611+00:00",
      "last_messages_count": 20,
      "last_problem_at": "2026-07-21T22:41:39.930544+00:00",
      "last_success_at": "2026-07-23T18:22:54.363611+00:00",
      "status": "ok",
      "successful_checks": 5867
    },
    "m4gastreams": {
      "checks": 4008,
      "consecutive_empty": 0,
      "consecutive_errors": 0,
      "last_checked_at": "2026-07-23T18:22:54.364531+00:00",
      "last_messages_count": 20,
      "last_problem_at": "2026-07-20T00:00:08.160887+00:00",
      "last_success_at": "2026-07-23T18:22:54.364531+00:00",
      "status": "ok",
      "successful_checks": 4007
    },
    "mAger_de_nuke": {
      "checks": 6096,
      "consecutive_empty": 0,
      "consecutive_errors": 0,
      "last_checked_at": "2026-07-23T18:22:54.362842+00:00",
      "last_messages_count": 11,
      "last_problem_at": "2026-07-22T07:53:29.985173+00:00",
      "last_success_at": "2026-07-23T18:22:54.362842+00:00",
      "status": "ok",
      "successful_checks": 6095,
      "transport_outages": 2
    },
    "magnojezking": {
      "checks": 5897,
      "consecutive_empty": 0,
      "consecutive_errors": 0,
      "last_checked_at": "2026-07-23T18:22:54.363583+00:00",
      "last_messages_count": 11,
      "last_success_at": "2026-07-23T18:22:54.363583+00:00",
      "status": "ok",
      "successful_checks": 5897,
      "transport_outages": 2
    },
    "mash1nkaaa": {
      "checks": 4008,
      "consecutive_empty": 0,
      "consecutive_errors": 0,
      "last_checked_at": "2026-07-23T18:22:54.364544+00:00",
      "last_messages_count": 10,
      "last_success_at": "2026-07-23T18:22:54.364544+00:00",
      "status": "ok",
      "successful_checks": 4008
    },
    "mashiromlbb": {
      "checks": 4008,
      "consecutive_empty": 0,
      "consecutive_errors": 0,
      "last_checked_at": "2026-07-23T18:22:54.364558+00:00",
      "last_messages_count": 19,
      "last_success_at": "2026-07-23T18:22:54.364558+00:00",
      "status": "ok",
      "successful_checks": 4008
    },
    "mayakmlbb": {
      "checks": 4008,
      "consecutive_empty": 0,
      "consecutive_errors": 0,
      "last_checked_at": "2026-07-23T18:22:54.364571+00:00",
      "last_messages_count": 20,
      "last_success_at": "2026-07-23T18:22:54.364571+00:00",
      "status": "ok",
      "successful_checks": 4008
    },
    "mechanogun": {
      "checks": 6096,
      "consecutive_empty": 0,
      "consecutive_errors": 0,
      "last_checked_at": "2026-07-23T18:22:54.362569+00:00",
      "last_messages_count": 20,
      "last_problem_at": "2026-07-22T07:38:19.344659+00:00",
      "last_success_at": "2026-07-23T18:22:54.362569+00:00",
      "status": "ok",
      "successful_checks": 6093,
      "transport_outages": 2
    },
    "meowbettt": {
      "checks": 6096,
      "consecutive_empty": 0,
      "consecutive_errors": 0,
      "last_checked_at": "2026-07-23T18:22:54.362857+00:00",
      "last_messages_count": 19,
      "last_success_at": "2026-07-23T18:22:54.362857+00:00",
      "status": "ok",
      "successful_checks": 6096,
      "transport_outages": 2
    },
    "mlbbcis": {
      "checks": 4008,
      "consecutive_empty": 0,
      "consecutive_errors": 0,
      "last_checked_at": "2026-07-23T18:22:54.364584+00:00",
      "last_messages_count": 18,
      "last_success_at": "2026-07-23T18:22:54.364584+00:00",
      "status": "ok",
      "successful_checks": 4008
    },
    "mlbbesports": {
      "checks": 4008,
      "consecutive_empty": 0,
      "consecutive_errors": 0,
      "last_checked_at": "2026-07-23T18:22:54.364599+00:00",
      "last_messages_count": 16,
      "last_problem_at": "2026-07-22T14:54:10.776418+00:00",
      "last_success_at": "2026-07-23T18:22:54.364599+00:00",
      "status": "ok",
      "successful_checks": 4007
    },
    "mrdaburud": {
      "checks": 4008,
      "consecutive_empty": 0,
      "consecutive_errors": 0,
      "last_checked_at": "2026-07-23T18:22:54.364626+00:00",
      "last_messages_count": 20,
      "last_success_at": "2026-07-23T18:22:54.364626+00:00",
      "status": "ok",
      "successful_checks": 4008
    },
    "mugretnug": {
      "checks": 4009,
      "consecutive_empty": 0,
      "consecutive_errors": 0,
      "last_checked_at": "2026-07-23T18:22:54.364061+00:00",
      "last_messages_count": 16,
      "last_problem_at": "2026-07-20T00:00:08.160289+00:00",
      "last_success_at": "2026-07-23T18:22:54.364061+00:00",
      "status": "ok",
      "successful_checks": 4008
    },
    "mugretnugbet": {
      "checks": 3362,
      "consecutive_empty": 0,
      "consecutive_errors": 0,
      "last_checked_at": "2026-07-23T18:22:54.364924+00:00",
      "last_messages_count": 20,
      "last_success_at": "2026-07-23T18:22:54.364924+00:00",
      "status": "ok",
      "successful_checks": 3362
    },
    "narodCast": {
      "checks": 6096,
      "consecutive_empty": 0,
      "consecutive_errors": 0,
      "last_checked_at": "2026-07-23T18:22:54.363257+00:00",
      "last_messages_count": 20,
      "last_success_at": "2026-07-23T18:22:54.363257+00:00",
      "status": "ok",
      "successful_checks": 6096,
      "transport_outages": 2
    },
    "nixtalk": {
      "checks": 6096,
      "consecutive_empty": 0,
      "consecutive_errors": 0,
      "last_checked_at": "2026-07-23T18:22:54.362682+00:00",
      "last_messages_count": 20,
      "last_problem_at": "2026-07-13T20:00:35.305024+00:00",
      "last_success_at": "2026-07-23T18:22:54.362682+00:00",
      "status": "ok",
      "successful_checks": 6095,
      "transport_outages": 2
    },
    "nucleartigeres": {
      "checks": 1263,
      "consecutive_empty": 0,
      "consecutive_errors": 0,
      "last_checked_at": "2026-07-23T18:22:54.364978+00:00",
      "last_messages_count": 20,
      "last_success_at": "2026-07-23T18:22:54.364978+00:00",
      "status": "ok",
      "successful_checks": 1263
    },
    "obshakstaya": {
      "checks": 6096,
      "consecutive_empty": 0,
      "consecutive_errors": 0,
      "last_checked_at": "2026-07-23T18:22:54.362733+00:00",
      "last_messages_count": 20,
      "last_problem_at": "2026-07-13T20:00:35.305087+00:00",
      "last_success_at": "2026-07-23T18:22:54.362733+00:00",
      "status": "ok",
      "successful_checks": 6095,
      "transport_outages": 2
    },
    "overdrivebet": {
      "checks": 5380,
      "consecutive_empty": 0,
      "consecutive_errors": 0,
      "last_checked_at": "2026-07-23T18:22:54.363710+00:00",
      "last_messages_count": 18,
      "last_problem_at": "2026-07-23T08:06:32.332454+00:00",
      "last_success_at": "2026-07-23T18:22:54.363710+00:00",
      "status": "ok",
      "successful_checks": 5379
    },
    "pandafx": {
      "checks": 6096,
      "consecutive_empty": 0,
      "consecutive_errors": 0,
      "last_checked_at": "2026-07-23T18:22:54.363124+00:00",
      "last_messages_count": 18,
      "last_success_at": "2026-07-23T18:22:54.363124+00:00",
      "status": "ok",
      "successful_checks": 6096,
      "transport_outages": 2
    },
    "pandafx2": {
      "checks": 5873,
      "consecutive_empty": 0,
      "consecutive_errors": 0,
      "last_checked_at": "2026-07-23T18:22:54.363345+00:00",
      "last_messages_count": 19,
      "last_success_at": "2026-07-23T18:22:54.363345+00:00",
      "status": "ok",
      "successful_checks": 5873
    },
    "pokerclubsochi": {
      "checks": 4008,
      "consecutive_empty": 0,
      "consecutive_errors": 0,
      "last_checked_at": "2026-07-23T18:22:54.364639+00:00",
      "last_messages_count": 19,
      "last_success_at": "2026-07-23T18:22:54.364639+00:00",
      "status": "ok",
      "successful_checks": 4008
    },
    "realmerussia": {
      "checks": 4008,
      "consecutive_empty": 0,
      "consecutive_errors": 0,
      "last_checked_at": "2026-07-23T18:22:54.364653+00:00",
      "last_messages_count": 19,
      "last_success_at": "2026-07-23T18:22:54.364653+00:00",
      "status": "ok",
      "successful_checks": 4008
    },
    "recrent": {
      "checks": 4008,
      "consecutive_empty": 0,
      "consecutive_errors": 0,
      "last_checked_at": "2026-07-23T18:22:54.364667+00:00",
      "last_messages_count": 20,
      "last_success_at": "2026-07-23T18:22:54.364667+00:00",
      "status": "ok",
      "successful_checks": 4008
    },
    "relaxcis": {
      "checks": 6096,
      "consecutive_empty": 0,
      "consecutive_errors": 0,
      "last_checked_at": "2026-07-23T18:22:54.363055+00:00",
      "last_messages_count": 18,
      "last_success_at": "2026-07-23T18:22:54.363055+00:00",
      "status": "ok",
      "successful_checks": 6096,
      "transport_outages": 2
    },
    "risenhaha": {
      "checks": 5873,
      "consecutive_empty": 0,
      "consecutive_errors": 0,
      "last_checked_at": "2026-07-23T18:22:54.363316+00:00",
      "last_messages_count": 20,
      "last_success_at": "2026-07-23T18:22:54.363316+00:00",
      "status": "ok",
      "successful_checks": 5873
    },
    "rodjerchamp": {
      "checks": 4008,
      "consecutive_empty": 0,
      "consecutive_errors": 0,
      "last_checked_at": "2026-07-23T18:22:54.364680+00:00",
      "last_messages_count": 6,
      "last_success_at": "2026-07-23T18:22:54.364680+00:00",
      "status": "ok",
      "successful_checks": 4008
    },
    "satir_Ilya": {
      "checks": 4009,
      "consecutive_empty": 0,
      "consecutive_errors": 0,
      "last_checked_at": "2026-07-23T18:22:54.364076+00:00",
      "last_messages_count": 20,
      "last_success_at": "2026-07-23T18:22:54.364076+00:00",
      "status": "ok",
      "successful_checks": 4009
    },
    "shadowkekw": {
      "checks": 6096,
      "consecutive_empty": 0,
      "consecutive_errors": 0,
      "last_checked_at": "2026-07-23T18:22:54.363024+00:00",
      "last_messages_count": 15,
      "last_success_at": "2026-07-23T18:22:54.363024+00:00",
      "status": "ok",
      "successful_checks": 6096,
      "transport_outages": 2
    },
    "shalashshpui": {
      "checks": 4008,
      "consecutive_empty": 0,
      "consecutive_errors": 0,
      "last_checked_at": "2026-07-23T18:22:54.364708+00:00",
      "last_messages_count": 18,
      "last_problem_at": "2026-07-20T00:00:08.161105+00:00",
      "last_success_at": "2026-07-23T18:22:54.364708+00:00",
      "status": "ok",
      "successful_checks": 4007
    },
    "shalfeycsgo": {
      "checks": 4008,
      "consecutive_empty": 0,
      "consecutive_errors": 0,
      "last_checked_at": "2026-07-23T18:22:54.364722+00:00",
      "last_messages_count": 20,
      "last_success_at": "2026-07-23T18:22:54.364722+00:00",
      "status": "ok",
      "successful_checks": 4008
    },
    "sheyl31": {
      "checks": 4008,
      "consecutive_empty": 0,
      "consecutive_errors": 0,
      "last_checked_at": "2026-07-23T18:22:54.364736+00:00",
      "last_messages_count": 14,
      "last_success_at": "2026-07-23T18:22:54.364736+00:00",
      "status": "ok",
      "successful_checks": 4008
    },
    "shoke": {
      "checks": 5725,
      "consecutive_empty": 0,
      "consecutive_errors": 0,
      "last_checked_at": "2026-07-23T18:22:54.363668+00:00",
      "last_messages_count": 20,
      "last_success_at": "2026-07-23T18:22:54.363668+00:00",
      "status": "ok",
      "successful_checks": 5725
    },
    "shoketg": {
      "checks": 6096,
      "consecutive_empty": 0,
      "consecutive_errors": 0,
      "last_checked_at": "2026-07-23T18:22:54.362793+00:00",
      "last_messages_count": 20,
      "last_problem_at": "2026-07-19T04:15:10.912057+00:00",
      "last_success_at": "2026-07-23T18:22:54.362793+00:00",
      "status": "ok",
      "successful_checks": 6094,
      "transport_outages": 2
    },
    "smurf_gigachad": {
      "checks": 6096,
      "consecutive_empty": 0,
      "consecutive_errors": 0,
      "last_checked_at": "2026-07-23T18:22:54.363100+00:00",
      "last_messages_count": 18,
      "last_success_at": "2026-07-23T18:22:54.363100+00:00",
      "status": "ok",
      "successful_checks": 6096,
      "transport_outages": 2
    },
    "solo322": {
      "checks": 5380,
      "consecutive_empty": 0,
      "consecutive_errors": 0,
      "last_checked_at": "2026-07-23T18:22:54.363724+00:00",
      "last_messages_count": 20,
      "last_success_at": "2026-07-23T18:22:54.363724+00:00",
      "status": "ok",
      "successful_checks": 5380
    },
    "solo_q_q": {
      "checks": 6096,
      "consecutive_empty": 0,
      "consecutive_errors": 0,
      "last_checked_at": "2026-07-23T18:22:54.362665+00:00",
      "last_messages_count": 20,
      "last_problem_at": "2026-07-13T20:00:35.305005+00:00",
      "last_success_at": "2026-07-23T18:22:54.362665+00:00",
      "status": "ok",
      "successful_checks": 6095,
      "transport_outages": 2
    },
    "spatich": {
      "checks": 4008,
      "consecutive_empty": 0,
      "consecutive_errors": 0,
      "last_checked_at": "2026-07-23T18:22:54.364749+00:00",
      "last_messages_count": 19,
      "last_success_at": "2026-07-23T18:22:54.364749+00:00",
      "status": "ok",
      "successful_checks": 4008
    },
    "starie_seniory": {
      "checks": 5897,
      "consecutive_empty": 0,
      "consecutive_errors": 0,
      "last_checked_at": "2026-07-23T18:22:54.363597+00:00",
      "last_messages_count": 20,
      "last_success_at": "2026-07-23T18:22:54.363597+00:00",
      "status": "ok",
      "successful_checks": 5897,
      "transport_outages": 2
    },
    "stavka_tv": {
      "checks": 4009,
      "consecutive_empty": 0,
      "consecutive_errors": 0,
      "last_checked_at": "2026-07-23T18:22:54.364089+00:00",
      "last_messages_count": 20,
      "last_success_at": "2026-07-23T18:22:54.364089+00:00",
      "status": "ok",
      "successful_checks": 4009
    },
    "stavkatv": {
      "checks": 4008,
      "consecutive_empty": 0,
      "consecutive_errors": 0,
      "last_checked_at": "2026-07-23T18:22:54.364763+00:00",
      "last_messages_count": 20,
      "last_problem_at": "2026-07-20T17:12:16.079836+00:00",
      "last_success_at": "2026-07-23T18:22:54.364763+00:00",
      "status": "ok",
      "successful_checks": 4007
    },
    "streamrosstg": {
      "checks": 4009,
      "consecutive_empty": 0,
      "consecutive_errors": 0,
      "last_checked_at": "2026-07-23T18:22:54.364103+00:00",
      "last_messages_count": 13,
      "last_success_at": "2026-07-23T18:22:54.364103+00:00",
      "status": "ok",
      "successful_checks": 4009
    },
    "torycs": {
      "checks": 4008,
      "consecutive_empty": 0,
      "consecutive_errors": 0,
      "last_checked_at": "2026-07-23T18:22:54.364776+00:00",
      "last_messages_count": 14,
      "last_problem_at": "2026-07-21T23:41:46.997070+00:00",
      "last_success_at": "2026-07-23T18:22:54.364776+00:00",
      "status": "ok",
      "successful_checks": 4006
    },
    "vane4kawyhm": {
      "checks": 4008,
      "consecutive_empty": 0,
      "consecutive_errors": 0,
      "last_checked_at": "2026-07-23T18:22:54.364790+00:00",
      "last_messages_count": 12,
      "last_problem_at": "2026-07-22T05:35:54.847600+00:00",
      "last_success_at": "2026-07-23T18:22:54.364790+00:00",
      "status": "ok",
      "successful_checks": 4007
    },
    "wfksiris": {
      "checks": 4008,
      "consecutive_empty": 0,
      "consecutive_errors": 0,
      "last_checked_at": "2026-07-23T18:22:54.364817+00:00",
      "last_messages_count": 7,
      "last_success_at": "2026-07-23T18:22:54.364817+00:00",
      "status": "ok",
      "successful_checks": 4008
    },
    "whylollybet": {
      "checks": 1632,
      "consecutive_empty": 0,
      "consecutive_errors": 0,
      "last_checked_at": "2026-07-23T18:22:54.364951+00:00",
      "last_messages_count": 17,
      "last_success_at": "2026-07-23T18:22:54.364951+00:00",
      "status": "ok",
      "successful_checks": 1632
    },
    "whylollycrry": {
      "checks": 6096,
      "consecutive_empty": 0,
      "consecutive_errors": 0,
      "last_checked_at": "2026-07-23T18:22:54.362919+00:00",
      "last_messages_count": 11,
      "last_problem_at": "2026-07-19T04:15:10.912215+00:00",
      "last_success_at": "2026-07-23T18:22:54.362919+00:00",
      "status": "ok",
      "successful_checks": 6095,
      "transport_outages": 2
    },
    "wonderbelkaML": {
      "checks": 4008,
      "consecutive_empty": 0,
      "consecutive_errors": 0,
      "last_checked_at": "2026-07-23T18:22:54.364830+00:00",
      "last_messages_count": 19,
      "last_success_at": "2026-07-23T18:22:54.364830+00:00",
      "status": "ok",
      "successful_checks": 4008
    },
    "zont1x": {
      "checks": 2792,
      "consecutive_empty": 0,
      "consecutive_errors": 0,
      "last_checked_at": "2026-07-23T18:22:54.364938+00:00",
      "last_messages_count": 20,
      "last_problem_at": "2026-07-22T07:24:13.011674+00:00",
      "last_success_at": "2026-07-23T18:22:54.364938+00:00",
      "status": "ok",
      "successful_checks": 2791
    },
    "zortelad": {
      "checks": 5897,
      "consecutive_empty": 0,
      "consecutive_errors": 0,
      "last_checked_at": "2026-07-23T18:22:54.363514+00:00",
      "last_messages_count": 17,
      "last_success_at": "2026-07-23T18:22:54.363514+00:00",
      "status": "ok",
      "successful_checks": 5897,
      "transport_outages": 2
    }
  },
  "version": 1
}
